[{"Nickname":"bblastock0","Active":false,"Real_Name":"Byran Blastock","Date_of_birth":"29/12/1996","Country_of_birth":"United States"},{"Nickname":"cbrendeke1","Active":true,"Real_Name":"Celle Brendeke","Date_of_birth":"11/03/1992","Country_of_birth":"Chile"},{"Nickname":"cmcrorie2","Active":false,"Real_Name":"Crystal McRorie","Date_of_birth":"02/12/1997","Country_of_birth":"Azerbaijan"},{"Nickname":"agyurko3","Active":false,"Real_Name":"Amargo Gyurko","Date_of_birth":"06/12/2003","Country_of_birth":"Thailand"},{"Nickname":"cjarley4","Active":true,"Real_Name":"Cybill Jarley","Date_of_birth":"31/12/1992","Country_of_birth":"Finland"},{"Nickname":"aandreucci5","Active":true,"Real_Name":"Angelica Andreucci","Date_of_birth":"09/07/1998","Country_of_birth":"Russia"},{"Nickname":"themshall6","Active":true,"Real_Name":"Trumann Hemshall","Date_of_birth":"25/11/2000","Country_of_birth":"Indonesia"},{"Nickname":"balleway7","Active":true,"Real_Name":"Bondy Alleway","Date_of_birth":"06/02/1994","Country_of_birth":"China"},{"Nickname":"cmougin8","Active":true,"Real_Name":"Calli Mougin","Date_of_birth":"20/05/2003","Country_of_birth":"Nigeria"},{"Nickname":"mpresswell9","Active":false,"Real_Name":"Morry Presswell","Date_of_birth":"10/01/2001","Country_of_birth":"Paraguay"},{"Nickname":"cseattera","Active":false,"Real_Name":"Chip Seatter","Date_of_birth":"20/04/1996","Country_of_birth":"Poland"},{"Nickname":"nharteb","Active":false,"Real_Name":"Nert Harte","Date_of_birth":"13/11/1991","Country_of_birth":"United States"},{"Nickname":"kveallc","Active":false,"Real_Name":"Kerwin Veall","Date_of_birth":"04/04/1999","Country_of_birth":"Portugal"},{"Nickname":"fniessend","Active":true,"Real_Name":"Frederique Niessen","Date_of_birth":"18/05/1996","Country_of_birth":"Canada"},{"Nickname":"ghamsteade","Active":true,"Real_Name":"Gennifer Hamstead","Date_of_birth":"26/04/1998","Country_of_birth":"Bulgaria"},{"Nickname":"jmccabef","Active":true,"Real_Name":"Jae McCabe","Date_of_birth":"12/11/2003","Country_of_birth":"Brazil"},{"Nickname":"jwilceg","Active":true,"Real_Name":"Jeremy Wilce","Date_of_birth":"13/05/1992","Country_of_birth":"Bulgaria"},{"Nickname":"twagstaffeh","Active":false,"Real_Name":"Terry Wagstaffe","Date_of_birth":"08/06/2000","Country_of_birth":"Indonesia"},{"Nickname":"mebyi","Active":true,"Real_Name":"Madelon Eby","Date_of_birth":"10/09/2001","Country_of_birth":"Ukraine"},{"Nickname":"lwallagej","Active":true,"Real_Name":"Leonard Wallage","Date_of_birth":"06/06/1993","Country_of_birth":"Indonesia"},{"Nickname":"dwilkiek","Active":true,"Real_Name":"Darice Wilkie","Date_of_birth":"21/09/2000","Country_of_birth":"China"},{"Nickname":"fgarritleyl","Active":false,"Real_Name":"Floris Garritley","Date_of_birth":"02/03/2000","Country_of_birth":"Argentina"},{"Nickname":"jraggittm","Active":false,"Real_Name":"Joshuah Raggitt","Date_of_birth":"12/04/2001","Country_of_birth":"Colombia"},{"Nickname":"nkaesmansn","Active":true,"Real_Name":"Nicholas Kaesmans","Date_of_birth":"22/10/1994","Country_of_birth":"Philippines"},{"Nickname":"rkermano","Active":true,"Real_Name":"Robbert Kerman","Date_of_birth":"02/02/2001","Country_of_birth":"Philippines"},{"Nickname":"lklimentyonokp","Active":false,"Real_Name":"Letisha Klimentyonok","Date_of_birth":"17/11/1996","Country_of_birth":"Malaysia"},{"Nickname":"sklugeq","Active":false,"Real_Name":"Sherry Kluge","Date_of_birth":"14/05/1992","Country_of_birth":"Portugal"},{"Nickname":"jpledgerr","Active":false,"Real_Name":"Johnathon Pledger","Date_of_birth":"01/04/2001","Country_of_birth":"Nigeria"},{"Nickname":"pkenders","Active":false,"Real_Name":"Prudence Kender","Date_of_birth":"04/05/1999","Country_of_birth":"Sudan"},{"Nickname":"erooneyt","Active":false,"Real_Name":"Ervin Rooney","Date_of_birth":"25/08/2003","Country_of_birth":"Poland"},{"Nickname":"mellwellu","Active":false,"Real_Name":"Maible Ellwell","Date_of_birth":"13/06/2003","Country_of_birth":"Kenya"},{"Nickname":"mperrotv","Active":true,"Real_Name":"Manya Perrot","Date_of_birth":"13/11/2002","Country_of_birth":"France"},{"Nickname":"ghurryw","Active":true,"Real_Name":"Grete Hurry","Date_of_birth":"01/03/1999","Country_of_birth":"Burkina Faso"},{"Nickname":"hcattlex","Active":true,"Real_Name":"Hagan Cattle","Date_of_birth":"06/10/1990","Country_of_birth":"China"},{"Nickname":"alupartiy","Active":false,"Real_Name":"Algernon Luparti","Date_of_birth":"07/01/2002","Country_of_birth":"United States"},{"Nickname":"owonforz","Active":false,"Real_Name":"Ozzy Wonfor","Date_of_birth":"31/03/1993","Country_of_birth":"Honduras"},{"Nickname":"npeiser10","Active":false,"Real_Name":"Nancy Peiser","Date_of_birth":"27/04/1993","Country_of_birth":"Poland"},{"Nickname":"sbrabyn11","Active":true,"Real_Name":"Stevena Brabyn","Date_of_birth":"10/07/1993","Country_of_birth":"Russia"},{"Nickname":"hde12","Active":true,"Real_Name":"Helge de Marco","Date_of_birth":"21/11/2000","Country_of_birth":"Canada"},{"Nickname":"bmenzies13","Active":false,"Real_Name":"Barthel Menzies","Date_of_birth":"14/08/1994","Country_of_birth":"Lithuania"},{"Nickname":"ebertie14","Active":true,"Real_Name":"Ericha Bertie","Date_of_birth":"31/07/1997","Country_of_birth":"Sweden"},{"Nickname":"ggonoude15","Active":false,"Real_Name":"Gae Gonoude","Date_of_birth":"08/08/1995","Country_of_birth":"Poland"},{"Nickname":"aadame16","Active":true,"Real_Name":"Abbe Adame","Date_of_birth":"27/01/1999","Country_of_birth":"Portugal"},{"Nickname":"khek17","Active":true,"Real_Name":"Kassie Hek","Date_of_birth":"06/07/1997","Country_of_birth":"Russia"},{"Nickname":"bbrundle18","Active":true,"Real_Name":"Berty Brundle","Date_of_birth":"18/08/2000","Country_of_birth":"China"},{"Nickname":"dfeldon19","Active":true,"Real_Name":"Dell Feldon","Date_of_birth":"07/10/1993","Country_of_birth":"Russia"},{"Nickname":"dtootal1a","Active":false,"Real_Name":"Dewain Tootal","Date_of_birth":"22/08/1997","Country_of_birth":"Portugal"},{"Nickname":"dportt1b","Active":false,"Real_Name":"Dennison Portt","Date_of_birth":"22/08/1995","Country_of_birth":"Senegal"},{"Nickname":"efarryann1c","Active":false,"Real_Name":"Eva Farryann","Date_of_birth":"23/12/2004","Country_of_birth":"Morocco"},{"Nickname":"hharnell1d","Active":true,"Real_Name":"Henri Harnell","Date_of_birth":"17/02/1990","Country_of_birth":"Brazil"},{"Nickname":"kbeagin1e","Active":true,"Real_Name":"Kara Beagin","Date_of_birth":"10/02/2003","Country_of_birth":"Honduras"},{"Nickname":"nsiverns1f","Active":true,"Real_Name":"Nathalie Siverns","Date_of_birth":"07/05/2004","Country_of_birth":"Cuba"},{"Nickname":"glidgely1g","Active":true,"Real_Name":"Granthem Lidgely","Date_of_birth":"24/04/1990","Country_of_birth":"Portugal"},{"Nickname":"hiddison1h","Active":true,"Real_Name":"Happy Iddison","Date_of_birth":"10/03/1994","Country_of_birth":"Indonesia"},{"Nickname":"tstilgo1i","Active":true,"Real_Name":"Towny Stilgo","Date_of_birth":"28/02/1999","Country_of_birth":"China"},{"Nickname":"glassen1j","Active":true,"Real_Name":"Greer Lassen","Date_of_birth":"16/04/2004","Country_of_birth":"Venezuela"},{"Nickname":"jlethcoe1k","Active":true,"Real_Name":"Joelly Lethcoe","Date_of_birth":"21/07/1999","Country_of_birth":"Nigeria"},{"Nickname":"pklimashevich1l","Active":true,"Real_Name":"Paulita Klimashevich","Date_of_birth":"11/03/1997","Country_of_birth":"Philippines"},{"Nickname":"bguiver1m","Active":true,"Real_Name":"Blane Guiver","Date_of_birth":"23/07/1991","Country_of_birth":"Sweden"},{"Nickname":"lgriffithe1n","Active":true,"Real_Name":"Laurel Griffithe","Date_of_birth":"26/07/2001","Country_of_birth":"Indonesia"},{"Nickname":"ddrewell1o","Active":false,"Real_Name":"Davidde Drewell","Date_of_birth":"25/10/1998","Country_of_birth":"United States"},{"Nickname":"stheml1p","Active":true,"Real_Name":"Sisely Theml","Date_of_birth":"16/11/2001","Country_of_birth":"Russia"},{"Nickname":"dthurlbeck1q","Active":false,"Real_Name":"Danie Thurlbeck","Date_of_birth":"23/04/2000","Country_of_birth":"Honduras"},{"Nickname":"nshorey1r","Active":true,"Real_Name":"Nert Shorey","Date_of_birth":"03/09/2001","Country_of_birth":"Argentina"},{"Nickname":"cmongenot1s","Active":false,"Real_Name":"Cordy Mongenot","Date_of_birth":"23/04/1992","Country_of_birth":"China"},{"Nickname":"khuggett1t","Active":false,"Real_Name":"Kippy Huggett","Date_of_birth":"20/03/1990","Country_of_birth":"Japan"},{"Nickname":"scaukill1u","Active":false,"Real_Name":"Stefano Caukill","Date_of_birth":"06/08/1994","Country_of_birth":"Argentina"},{"Nickname":"tsylett1v","Active":true,"Real_Name":"Thekla Sylett","Date_of_birth":"25/02/1995","Country_of_birth":"Philippines"},{"Nickname":"njope1w","Active":false,"Real_Name":"Nolly Jope","Date_of_birth":"15/07/1993","Country_of_birth":"Japan"},{"Nickname":"dmoukes1x","Active":false,"Real_Name":"Dag Moukes","Date_of_birth":"26/08/1997","Country_of_birth":"China"},{"Nickname":"nkennard1y","Active":false,"Real_Name":"Normand Kennard","Date_of_birth":"08/07/1999","Country_of_birth":"Argentina"},{"Nickname":"nleiden1z","Active":false,"Real_Name":"Nellie Leiden","Date_of_birth":"01/10/1997","Country_of_birth":"Indonesia"},{"Nickname":"dblinkhorn20","Active":false,"Real_Name":"Delaney Blinkhorn","Date_of_birth":"18/07/2001","Country_of_birth":"Russia"},{"Nickname":"vbugler21","Active":true,"Real_Name":"Vladimir Bugler","Date_of_birth":"04/09/1996","Country_of_birth":"China"},{"Nickname":"sparvin22","Active":true,"Real_Name":"Sapphire Parvin","Date_of_birth":"22/11/1998","Country_of_birth":"Slovenia"},{"Nickname":"rmckeachie23","Active":false,"Real_Name":"Rori McKeachie","Date_of_birth":"12/04/1991","Country_of_birth":"Portugal"},{"Nickname":"apetrie24","Active":false,"Real_Name":"Annadiana Petrie","Date_of_birth":"05/04/1999","Country_of_birth":"Poland"},{"Nickname":"efronks25","Active":true,"Real_Name":"Elbert Fronks","Date_of_birth":"03/10/1997","Country_of_birth":"Kazakhstan"},{"Nickname":"abillborough26","Active":false,"Real_Name":"Adena Billborough","Date_of_birth":"30/08/1994","Country_of_birth":"Portugal"},{"Nickname":"rsculley27","Active":true,"Real_Name":"Rivkah Sculley","Date_of_birth":"10/01/1994","Country_of_birth":"Indonesia"},{"Nickname":"bmcgloin28","Active":true,"Real_Name":"Bernette McGloin","Date_of_birth":"02/08/2000","Country_of_birth":"China"},{"Nickname":"wdonett29","Active":true,"Real_Name":"Wilden Donett","Date_of_birth":"30/11/2003","Country_of_birth":"Indonesia"},{"Nickname":"mvize2a","Active":false,"Real_Name":"Marj Vize","Date_of_birth":"25/11/1990","Country_of_birth":"Czech Republic"},{"Nickname":"apoundesford2b","Active":true,"Real_Name":"Alanna Poundesford","Date_of_birth":"04/07/2001","Country_of_birth":"China"},{"Nickname":"wstennet2c","Active":false,"Real_Name":"Wilbur Stennet","Date_of_birth":"14/07/2000","Country_of_birth":"Argentina"},{"Nickname":"amcnelis2d","Active":true,"Real_Name":"Allie McNelis","Date_of_birth":"01/09/2001","Country_of_birth":"China"},{"Nickname":"cscarsbrooke2e","Active":true,"Real_Name":"Celka Scarsbrooke","Date_of_birth":"19/12/2002","Country_of_birth":"China"},{"Nickname":"rkennaird2f","Active":true,"Real_Name":"Rem Kennaird","Date_of_birth":"09/10/1990","Country_of_birth":"Russia"},{"Nickname":"ivalti2g","Active":false,"Real_Name":"Ilario Valti","Date_of_birth":"15/06/1999","Country_of_birth":"Poland"},{"Nickname":"foilier2h","Active":true,"Real_Name":"Francklyn OIlier","Date_of_birth":"05/02/1990","Country_of_birth":"Philippines"},{"Nickname":"lmacillrick2i","Active":false,"Real_Name":"Lisle MacIllrick","Date_of_birth":"11/03/2004","Country_of_birth":"Tanzania"},{"Nickname":"kcheine2j","Active":true,"Real_Name":"Klemens Cheine","Date_of_birth":"06/10/1994","Country_of_birth":"Canada"},{"Nickname":"oastridge2k","Active":true,"Real_Name":"Olva Astridge","Date_of_birth":"31/10/1996","Country_of_birth":"Indonesia"},{"Nickname":"esearsby2l","Active":true,"Real_Name":"Ephrayim Searsby","Date_of_birth":"09/11/1993","Country_of_birth":"Belarus"},{"Nickname":"btrelease2m","Active":true,"Real_Name":"Barbey Trelease","Date_of_birth":"02/05/1994","Country_of_birth":"Syria"},{"Nickname":"etootin2n","Active":false,"Real_Name":"Emelita Tootin","Date_of_birth":"14/02/2001","Country_of_birth":"Czech Republic"},{"Nickname":"zcolegate2o","Active":false,"Real_Name":"Zacherie Colegate","Date_of_birth":"11/04/1999","Country_of_birth":"Indonesia"},{"Nickname":"pbuchanan2p","Active":true,"Real_Name":"Pierrette Buchanan","Date_of_birth":"22/01/1991","Country_of_birth":"Philippines"},{"Nickname":"mkiefer2q","Active":false,"Real_Name":"Maye Kiefer","Date_of_birth":"24/12/1991","Country_of_birth":"Japan"},{"Nickname":"ppawson2r","Active":true,"Real_Name":"Pooh Pawson","Date_of_birth":"15/12/2002","Country_of_birth":"Guatemala"}]